lkr/__init__.py
lkr/auth_service.py
lkr/classes.py
lkr/constants.py
lkr/exceptions.py
lkr/logging.py
lkr/main.py
lkr/types.py
lkr/utils.py
lkr/auth/__init__.py
lkr/auth/main.py
lkr/auth/oauth.py
lkr/embed/main.py
lkr/embed/observability/constants.py
lkr/embed/observability/create_sso_embed_url.py
lkr/embed/observability/embed_container.html
lkr/embed/observability/embed_server.py
lkr/embed/observability/utils.py
lkr_cli-0.0.2.dist-info/METADATA
lkr_cli-0.0.2.dist-info/WHEEL
lkr_cli-0.0.2.dist-info/entry_points.txt
lkr_cli-0.0.2.dist-info/licenses/LICENSE
lkr_cli-0.0.2.dist-info/RECORD
