Metadata-Version: 2.4
Name: lkr-cli
Version: 0.0.2
Summary: lkr: a command line interface for looker
Author: bwebs
License-Expression: MIT
License-File: LICENSE
Requires-Python: >=3.12
Requires-Dist: cryptography>=42.0.0
Requires-Dist: looker-sdk>=25.4.0
Requires-Dist: pick>=2.4.0
Requires-Dist: pydantic>=2.11.4
Requires-Dist: pydash>=8.0.5
Requires-Dist: requests>=2.31.0
Requires-Dist: structlog>=25.3.0
Requires-Dist: typer>=0.15.2
